maskara/__init__.py
maskara/maskara.py
maskara-1.0.0.data/scripts/maskara.py
maskara-1.0.0.dist-info/LICENSE
maskara-1.0.0.dist-info/METADATA
maskara-1.0.0.dist-info/WHEEL
maskara-1.0.0.dist-info/entry_points.txt
maskara-1.0.0.dist-info/top_level.txt
maskara-1.0.0.dist-info/RECORD
