Metadata-Version: 2.1
Name: maskara
Version: 1.0.0
Summary: maskara
Home-page: https://github.com/Desperate-Dan/maskara
Author: Daniel Maloney
Author-email: dmaloney@ed.ac.uk
License-File: LICENSE
Requires-Dist: biopython
Requires-Dist: pysam
Requires-Dist: numpy
